nbwc/__init__.py
nbwc/nbwc.py
nbwc/tests/eg_nb.Rmd
nbwc/tests/eg_nb.ipynb
nbwc/tests/test_counts.py
nbwc-0.1a0.dist-info/entry_points.txt
nbwc-0.1a0.dist-info/LICENSE
nbwc-0.1a0.dist-info/WHEEL
nbwc-0.1a0.dist-info/METADATA
nbwc-0.1a0.dist-info/RECORD
