Metadata-Version: 2.1
Name: nbwc
Version: 0.1a0
Summary: Notebook wordcount
Author-email: Matthew Brett <matthew.brett@gmail.com>
Requires-Python: >=3.6
Classifier: License :: OSI Approved :: BSD License
Classifier: Programming Language :: Python :: 3
Requires-Dist: jupytext
Requires-Dist: nltk
Project-URL: Home, https://github.com/matthew-brett/nbwc
